{
  "version": 1,
  "entries": [
    {
      "permissionSet": "showcase_auditor",
      "object": "showcase_inquiry",
      "create": false,
      "read": true,
      "edit": false,
      "delete": false,
      "viewAllRecords": true,
      "modifyAllRecords": false,
      "sharingModel": "private"
    },
    {
      "permissionSet": "showcase_auditor",
      "object": "showcase_invoice",
      "create": false,
      "read": true,
      "edit": false,
      "delete": false,
      "viewAllRecords": true,
      "modifyAllRecords": false,
      "sharingModel": "public_read_write"
    },
    {
      "permissionSet": "showcase_auditor",
      "object": "showcase_invoice_line",
      "create": false,
      "read": true,
      "edit": false,
      "delete": false,
      "viewAllRecords": true,
      "modifyAllRecords": false,
      "sharingModel": "controlled_by_parent"
    },
    {
      "permissionSet": "showcase_auditor",
      "object": "showcase_private_note",
      "create": false,
      "read": true,
      "edit": false,
      "delete": false,
      "viewAllRecords": true,
      "modifyAllRecords": false,
      "sharingModel": "private"
    },
    {
      "permissionSet": "showcase_contributor",
      "object": "showcase_account",
      "create": false,
      "read": true,
      "edit": false,
      "delete": false,
      "viewAllRecords": false,
      "modifyAllRecords": false,
      "sharingModel": "public_read_write"
    },
    {
      "permissionSet": "showcase_contributor",
      "object": "showcase_invoice",
      "create": true,
      "read": true,
      "edit": true,
      "delete": false,
      "viewAllRecords": false,
      "modifyAllRecords": false,
      "sharingModel": "public_read_write"
    },
    {
      "permissionSet": "showcase_contributor",
      "object": "showcase_invoice_line",
      "create": true,
      "read": true,
      "edit": true,
      "delete": false,
      "viewAllRecords": false,
      "modifyAllRecords": false,
      "sharingModel": "controlled_by_parent"
    },
    {
      "permissionSet": "showcase_contributor",
      "object": "showcase_project",
      "create": false,
      "read": true,
      "edit": true,
      "delete": false,
      "viewAllRecords": false,
      "modifyAllRecords": false,
      "sharingModel": "public_read_write"
    },
    {
      "permissionSet": "showcase_contributor",
      "object": "showcase_task",
      "create": true,
      "read": true,
      "edit": true,
      "delete": false,
      "viewAllRecords": false,
      "modifyAllRecords": false,
      "sharingModel": "public_read_write"
    },
    {
      "permissionSet": "showcase_executive",
      "object": "showcase_inquiry",
      "create": false,
      "read": true,
      "edit": false,
      "delete": false,
      "viewAllRecords": false,
      "modifyAllRecords": false,
      "readScope": "org",
      "sharingModel": "private"
    },
    {
      "permissionSet": "showcase_executive",
      "object": "showcase_private_note",
      "create": false,
      "read": true,
      "edit": false,
      "delete": false,
      "viewAllRecords": false,
      "modifyAllRecords": false,
      "readScope": "org",
      "sharingModel": "private"
    },
    {
      "permissionSet": "showcase_field_ops_delegate",
      "object": "sys_business_unit",
      "create": false,
      "read": true,
      "edit": false,
      "delete": false,
      "viewAllRecords": false,
      "modifyAllRecords": false
    },
    {
      "permissionSet": "showcase_field_ops_delegate",
      "object": "sys_business_unit_member",
      "create": false,
      "read": true,
      "edit": false,
      "delete": false,
      "viewAllRecords": false,
      "modifyAllRecords": false
    },
    {
      "permissionSet": "showcase_field_ops_delegate",
      "object": "sys_permission_set",
      "create": false,
      "read": true,
      "edit": false,
      "delete": false,
      "viewAllRecords": false,
      "modifyAllRecords": false
    },
    {
      "permissionSet": "showcase_field_ops_delegate",
      "object": "sys_position",
      "create": false,
      "read": true,
      "edit": false,
      "delete": false,
      "viewAllRecords": false,
      "modifyAllRecords": false
    },
    {
      "permissionSet": "showcase_field_ops_delegate",
      "object": "sys_user",
      "create": false,
      "read": true,
      "edit": false,
      "delete": false,
      "viewAllRecords": false,
      "modifyAllRecords": false
    },
    {
      "permissionSet": "showcase_field_ops_delegate",
      "object": "sys_user_position",
      "create": true,
      "read": true,
      "edit": true,
      "delete": true,
      "viewAllRecords": false,
      "modifyAllRecords": false
    },
    {
      "permissionSet": "showcase_guest_portal",
      "object": "showcase_announcement",
      "create": false,
      "read": true,
      "edit": false,
      "delete": false,
      "viewAllRecords": false,
      "modifyAllRecords": false,
      "sharingModel": "public_read"
    },
    {
      "permissionSet": "showcase_guest_portal",
      "object": "showcase_inquiry",
      "create": true,
      "read": false,
      "edit": false,
      "delete": false,
      "viewAllRecords": false,
      "modifyAllRecords": false,
      "sharingModel": "private"
    },
    {
      "permissionSet": "showcase_manager",
      "object": "showcase_contact",
      "create": false,
      "read": true,
      "edit": false,
      "delete": false,
      "viewAllRecords": false,
      "modifyAllRecords": false,
      "readScope": "org",
      "sharingModel": "private"
    },
    {
      "permissionSet": "showcase_manager",
      "object": "showcase_inquiry",
      "create": false,
      "read": true,
      "edit": true,
      "delete": false,
      "viewAllRecords": false,
      "modifyAllRecords": false,
      "readScope": "org",
      "writeScope": "own",
      "sharingModel": "private"
    },
    {
      "permissionSet": "showcase_member_default",
      "object": "showcase_account",
      "create": false,
      "read": true,
      "edit": false,
      "delete": false,
      "viewAllRecords": false,
      "modifyAllRecords": false,
      "sharingModel": "public_read_write"
    },
    {
      "permissionSet": "showcase_member_default",
      "object": "showcase_announcement",
      "create": false,
      "read": true,
      "edit": false,
      "delete": false,
      "viewAllRecords": false,
      "modifyAllRecords": false,
      "sharingModel": "public_read"
    },
    {
      "permissionSet": "showcase_member_default",
      "object": "showcase_inquiry",
      "create": true,
      "read": true,
      "edit": false,
      "delete": false,
      "viewAllRecords": false,
      "modifyAllRecords": false,
      "sharingModel": "private"
    },
    {
      "permissionSet": "showcase_member_default",
      "object": "showcase_private_note",
      "create": true,
      "read": true,
      "edit": true,
      "delete": false,
      "viewAllRecords": false,
      "modifyAllRecords": false,
      "sharingModel": "private"
    },
    {
      "permissionSet": "showcase_member_default",
      "object": "showcase_product",
      "create": false,
      "read": true,
      "edit": false,
      "delete": false,
      "viewAllRecords": false,
      "modifyAllRecords": false,
      "sharingModel": "public_read_write"
    },
    {
      "permissionSet": "showcase_member_default",
      "object": "showcase_project",
      "create": false,
      "read": true,
      "edit": false,
      "delete": false,
      "viewAllRecords": false,
      "modifyAllRecords": false,
      "sharingModel": "public_read_write"
    },
    {
      "permissionSet": "showcase_member_default",
      "object": "showcase_task",
      "create": true,
      "read": true,
      "edit": false,
      "delete": false,
      "viewAllRecords": false,
      "modifyAllRecords": false,
      "sharingModel": "public_read_write"
    },
    {
      "permissionSet": "showcase_ops",
      "object": "showcase_announcement",
      "create": true,
      "read": true,
      "edit": true,
      "delete": true,
      "viewAllRecords": false,
      "modifyAllRecords": true,
      "sharingModel": "public_read"
    },
    {
      "permissionSet": "showcase_ops",
      "object": "showcase_inquiry",
      "create": false,
      "read": true,
      "edit": true,
      "delete": false,
      "viewAllRecords": false,
      "modifyAllRecords": false,
      "readScope": "org",
      "writeScope": "org",
      "sharingModel": "private"
    },
    {
      "permissionSet": "showcase_ops",
      "object": "showcase_invoice",
      "create": false,
      "read": true,
      "edit": false,
      "delete": false,
      "viewAllRecords": false,
      "modifyAllRecords": false,
      "sharingModel": "public_read_write"
    }
  ]
}
